MANIFEST.in
README.md
requirements.txt
setup.py
re3py/__init__.py
re3py.egg-info/PKG-INFO
re3py.egg-info/SOURCES.txt
re3py.egg-info/dependency_links.txt
re3py.egg-info/not-zip-safe
re3py.egg-info/requires.txt
re3py.egg-info/top_level.txt
re3py/data/__init__.py
re3py/data/data_and_statistics.py
re3py/data/relation.py
re3py/data/task_settings.py
re3py/eval/__init__.py
re3py/eval/evaluation.py
re3py/learners/__init__.py
re3py/learners/boosting.py
re3py/learners/predictive_model.py
re3py/learners/random_forest.py
re3py/learners/tree.py
re3py/learners/core/__init__.py
re3py/learners/core/aggregators.py
re3py/learners/core/communicate_with_java.py
re3py/learners/core/comparators.py
re3py/learners/core/heuristic.py
re3py/learners/core/tree_node_split.py
re3py/learners/core/variables.py
re3py/ranking/__init__.py
re3py/ranking/ensemble_ranking.py
re3py/utilities/__init__.py
re3py/utilities/cross_validation.py
re3py/utilities/my_exceptions.py
re3py/utilities/my_memo.py
re3py/utilities/my_utils.py
re3py/utilities/table_to_relations.py
re3py/utilities/user_defined_relation.py